deepwiki_export/__init__.py
deepwiki_export/chunk_processor.py
deepwiki_export/cli_tool.py
deepwiki_export/extract_markdown_from_html.py
deepwiki_export/save_markdown_from_url.py
deepwiki_export/utils.py
deepwiki_export-0.2.1.dist-info/entry_points.txt
deepwiki_export-0.2.1.dist-info/LICENSE
deepwiki_export-0.2.1.dist-info/METADATA
deepwiki_export-0.2.1.dist-info/WHEEL
deepwiki_export-0.2.1.dist-info/RECORD
