Metadata-Version: 2.3
Name: deepwiki-export
Version: 0.2.1
Summary: Downloads and processes content from DeepWiki/GitHub URLs into Markdown.
License: MIT
Keywords: deepwiki,markdown,export,cli,github
Author: 刘世超(RobirdLiu)
Author-email: RobirdLiu@Gmail.com
Requires-Python: >=3.12
Classifier: License :: OSI Approved :: MIT License
Classifier: Programming Language :: Python :: 3
Classifier: Programming Language :: Python :: 3.12
Classifier: Programming Language :: Python :: 3.13
Requires-Dist: requests (>=2.32.3,<3.0.0)
Requires-Dist: typer[all] (>=0.12.3,<0.13.0)
Project-URL: Homepage, https://github.com/yourusername/deepwiki-export
Project-URL: Repository, https://github.com/yourusername/deepwiki-export
